nonemoji/__init__.py
nonemoji/__main__.py
nonemoji/cli.py
nonemoji/command.py
nonemoji/emoji.py
nonemoji/feature.py
nonemoji-0.1.4.dist-info/METADATA
nonemoji-0.1.4.dist-info/WHEEL
nonemoji-0.1.4.dist-info/entry_points.txt
nonemoji-0.1.4.dist-info/RECORD
